datadog_serverless_compat/__init__.py
datadog_serverless_compat/bin/linux-amd64/datadog-serverless-compat
datadog_serverless_compat/bin/windows-amd64/datadog-serverless-compat.exe
datadog_serverless_compat/logger.py
datadog_serverless_compat/main.py
datadog_serverless_compat-0.8.1.dist-info/LICENSE
datadog_serverless_compat-0.8.1.dist-info/LICENSE-3rdparty.csv
datadog_serverless_compat-0.8.1.dist-info/METADATA
datadog_serverless_compat-0.8.1.dist-info/NOTICE
datadog_serverless_compat-0.8.1.dist-info/WHEEL
datadog_serverless_compat-0.8.1.dist-info/RECORD
